faber_fireplace/__init__.py
faber_fireplace/faber.py
faber_fireplace-0.0.2.dist-info/METADATA
faber_fireplace-0.0.2.dist-info/WHEEL
faber_fireplace-0.0.2.dist-info/licenses/LICENSE
faber_fireplace-0.0.2.dist-info/RECORD
