Metadata-Version: 2.1
Name: faber_fireplace
Version: 0.0.2
Summary: Python package for controlling a Faber fireplace
Project-URL: Homepage, https://github.com/Andreas-Utkilen/faber_fireplace
Project-URL: Bug Tracker, https://github.com/Andreas-Utkilen/faber_fireplace/issues
Author-email: Andreas Traa Utkilen <andreastraautkilen@gmail.com>
License-File: LICENSE
Classifier: License :: OSI Approved :: MIT License
Classifier: Operating System :: OS Independent
Classifier: Programming Language :: Python :: 3
Requires-Python: >=3.7
